Workbook

Sheet Mode d'emploi
A1: Gel 2 — validation des indicateurs de la dimension « Santé »
A3: Comment remplir ce classeur (validation par exception, charte §3.6, décision D20)
A4: 1. Ouvrez l'onglet « Validation ». Chaque ligne est un indicateur candidat (une fiche YAML dans le dépôt), regroupé par sous-thème puis par famille ; la variante principale de chaque famille est en tête.
A5: 2. Les colonnes grises sont informatives. La colonne « Recommandation de l'agent » et son motif résument l'analyse ; la colonne « Décision par défaut » indique ce qui s'appliquera si vous ne remplissez rien.
A6: « Socle proposé » = oui : l'agent propose de cocher l'indicateur par défaut (décision D41 : les incontournables et une fiche principale par sous-thème de la dimension, 8 au plus) ; sa décision par défaut est alors retenu_socle. L'onglet « Synthèse » compte le socle par sous-thème.
A7: 3. Ne remplissez la colonne jaune « Votre décision » que là où vous divergez ou hésitez. Valeurs possibles (liste déroulante) :
A8: retenu = disponible dans l'outil, non coché par défaut ;
A9: retenu_socle = disponible ET coché par défaut dans la configuration de référence ;
A10: ecarte = non retenu (indiquez pourquoi dans le commentaire) ;
A11: a_discuter = vous voulez en parler avant de trancher (la session mère vous posera la question).
A12: 4. Le commentaire est libre ; il est lu et conservé dans la fiche.
A13: 5. Enregistrez le fichier au même endroit, sous le même nom : la session mère le relit automatiquement.
... A23: Exemple de ligne remplie : décision « ecarte », commentaire « doublon de la série INSEE équivalente ; garder la variante INSEE ».

Sheet Validation
A1: Sous-thème | B1: Famille | C1: Identifiant | D1: Libellé | E1: Variante principale | F1: Définition courte | G1: Sens | H1: Unité | I1: Source | J1: Série (identifiant) | K1: Période | L1: Type | M1: Déclaratif | N1: Composite | O1: Incontournable | P1: Socle proposé | Q1: Recommandation de l'agent | R1: Motif de la recommandation | S1: Décision par défaut (si vous ne remplissez rien) | T1: Votre décision (liste déroulante) | U1: Votre commentaire
A2: accès aux soins | B2: besoins_soins_dentaires | C2: besoins_soins_dentaires_non_satisfaits | D2: Besoins de soins dentaires non satisfaits | E2: oui | F2: Part des personnes de 16 ans ou plus déclarant avoir eu besoin d'un examen ou d'un traitement dentaire sans l'obtenir parce qu'il était trop cher, trop éloigné ou à cause d'une liste d'attente (enquête SRCV). | G2: bas | H2: % des 16 ans ou plus | I2: Eurostat (d'après l'INSEE, enquête SRCV) — hlth_silc_09 (besoins dentaires non satisfaits par raison principale) | J2: hlth_silc_09?freq=A&unit=PC&quant_inc=TOTAL&reason=TXP_TFAR_WLIST&age=Y_GE16&sex=T&geo=FR | K2: 2008-2025 (18 points, annuelle) | L2: resultat | M2: non | N2: non | O2: non | P2: non | Q2: retenir | R2: Soins les plus souvent non obtenus, annuels de 2008 à 2025 (4,2 % en 2008, 7,0 % en 2024, 6,5 % en 2025), concept distinct des soins médicaux et non substituable (D35). | S2: retenu
A3: accès aux soins | B3: besoins_soins_non_satisfaits | C3: besoins_soins_non_satisfaits | D3: Besoins de soins médicaux non satisfaits | E3: oui | F3: Part des personnes de 16 ans ou plus déclarant avoir eu besoin d'un examen ou d'un traitement médical au cours des 12 derniers mois sans l'obtenir parce qu'il était trop cher, trop éloigné ou à cause d'une liste … | G3: bas | H3: % des 16 ans ou plus | I3: Eurostat (d'après l'INSEE, enquête SRCV) — sdg_03_60 (besoins auto-déclarés de traitement médical non satisfaits) | J3: sdg_03_60?freq=A&age=Y_GE16&sex=T&reason=TXP_TFAR_WLIST&unit=PC&quant_inc=TOTAL&geo=FR | K3: 2008-2025 (18 points, annuelle) | L3: resultat | M3: non | N3: non | O3: non | P3: oui | Q3: retenir | R3: Indicateur du tableau de bord ODD de l'UE et du cadre Qualité de vie d'Eurostat, annuel de 2008 à 2025 (1,9 % en 2008, 4,1 % en 2024, 3,7 % en 2025). | S3: retenu_socle
A4: accès aux soins | B4: besoins_soins_non_satisfaits | C4: couverture_sanitaire_universelle | D4: Indice de couverture des services de santé essentiels (OMS) | E4: non | F4: Indice de 0 à 100 de couverture des services de santé essentiels (santé reproductive et infantile, maladies infectieuses, maladies non transmissibles, capacité et accès aux services), indicateur ODD 3.8.1 calculé par … | G4: haut | H4: indice (0 à 100) | I4: OCDE (d'après l'OMS) — Base ODD de l'OCDE, objectif 3 (indicateur 3.8.1) | J4: odd_3 : 3_8_1_SH_ACS_UNHC._T._T._T._T._T.IX | K4: 2000-2021 (7 points, irreguliere) | L4: resultat | M4: non | N4: oui | O4: non | P4: non | Q4: retenir_variante | R4: Indicateur du Doughnut (seuil de privation à 60) et de la cible ODD 3.8, 7 années de 2000 à 2021 (85 en 2021) admises comme série irrégulière (D17). | S4: retenu
A5: accès aux soins | B5: besoins_soins_non_satisfaits | C5: renoncement_soins_financier | D5: Renoncement aux soins médicaux pour raisons financières | E5: non | F5: Part des personnes de 16 ans ou plus déclarant avoir renoncé à un examen ou à un traitement médical dont elles avaient besoin parce qu'il était trop cher (enquête SRCV, volet français d'EU-SILC). | G5: bas | H5: % des 16 ans ou plus | I5: Eurostat (d'après l'INSEE, enquête SRCV) — hlth_silc_08 (besoins non satisfaits par raison principale), raison « trop cher » | J5: hlth_silc_08?freq=A&unit=PC&quant_inc=TOTAL&reason=TXP&age=Y_GE16&sex=T&geo=FR | K5: 2008-2025 (18 points, annuelle) | L5: resultat | M5: non | N5: non | O5: non | P5: non | Q5: retenir_variante | R5: Composante financière des besoins non satisfaits, annuelle de 2008 à 2025 (1,6 % en 2008, 1,9 % en 2025), identique sur 2010-2023 à l'indicateur national ODD 3.i7a de l'INSEE. | S5: retenu
A6: accès aux soins | B6: densite_medecins | C6: densite_medecins_generalistes | D6: Densité de médecins généralistes | E6: oui | F6: Nombre de médecins généralistes en activité pour 100 000 habitants, France (INSEE d'après le répertoire RPPS, DREES). | G6: haut | H6: médecins pour 100 000 habitants | I6: INSEE (d'après la DREES, RPPS) — Densité des professionnels de santé (BDM) | J6: 010761075 | K6: 2012-2025 (14 points, annuelle) | L6: moyen | M6: non | N6: non | O6: non | P6: non | Q6: retenir | R6: Mesure de l'offre de soins de premier recours admise comme moyen (D19), annuelle de 2012 à 2025 (155 pour 100 000 en 2012, 145 en 2024, 146 en 2025), en baisse sur la période. | S6: retenu
A7: accès aux soins | B7: manque_medecins_percu | C7: manque_medecins_percu | D7: Personnes estimant manquer de médecins généralistes à proximité | E7: oui | F7: Part des personnes interrogées par le baromètre d'opinion de la DREES qui estiment qu'il n'y a « pas assez » de médecins généralistes à proximité de chez elles (question SA09_1, modalité 3, non-réponses au dénominateur, … | G7: bas | H7: % des répondants | I7: DREES (baromètre d'opinion) — Baromètre d'opinion de la DREES (data.drees, jeu 431_le-barometre-d-opinion), microdonnées pondérées | J7: data.drees.solidarites-sante.gouv.fr, jeu 431_le-barometre-d-opinion, pièce jointe barometre2000_2025_diff_csv ; variable SA09_1, modalités 3 | K7: 2002-2025 (11 points, irreguliere) | L7: resultat | M7: oui | N7: non | O7: non | P7: non | Q7: retenir | R7: Seule mesure ressentie de l'offre de soins de proximité, 11 vagues de 2002 à 2025 (20,7 % en 2002, 55,8 % en 2025), valeur 2025 recoupée sur le tableau officiel de la DREES (55,76 %). | S7: retenu
A8: accès aux soins | B8: reste_a_charge_menages | C8: reste_a_charge_menages | D8: Part des paiements directs des ménages dans la dépense de santé | E8: oui | F8: Paiements directs des ménages (reste à charge après assurance maladie obligatoire et complémentaire) en pourcentage de la dépense courante de santé, France (comptes de la santé, système SHA). | G8: bas | H8: % de la dépense courante de santé | I8: Eurostat (d'après la DREES, comptes de la santé) — hlth_sha11_hf (dépenses de santé par mécanisme de financement), HF3 | J8: hlth_sha11_hf?freq=A&unit=PC_CHE&icha11_hf=HF3&geo=FR | K8: 2006-2025 (20 points, annuelle) | L8: moyen | M8: non | N8: non | O8: non | P8: non | Q8: retenir | R8: Mesure de la protection financière des ménages face aux soins, annuelle de 2006 à 2025 (9,36 % en 2006, 11,96 % en 2010, 10,32 % en 2025, provisoire), qui complète le renoncement pour raisons financières. | S8: retenu
A9: causes de décès | B9: mortalite_cancer | C9: mortalite_cancer | D9: Mortalité par cancer | E9: oui | F9: Taux standardisé de mortalité par tumeurs malignes (CIM-10 C00-C97), tous âges, France (population standard européenne 2013). | G9: bas | H9: décès pour 100 000 habitants (taux standardisé) | I9: Eurostat (d'après l'INSEE-CépiDc) — hlth_cd_asdr2 (causes de décès, taux standardisés) | J9: hlth_cd_asdr2?freq=A&unit=RT&sex=T&age=TOTAL&icd10=C&geo=FR | K9: 2011-2023 (13 points, annuelle) | L9: resultat | M9: non | N9: non | O9: non | P9: non | Q9: retenir | R9: Première cause de décès en taux standardisé sur toute la période 2011-2023 (253,11 pour 100 000 en 2011, 218,58 en 2023), série annuelle sans drapeau. | S9: retenu
A10: causes de décès | B10: mortalite_cardiovasculaire | C10: mortalite_cardiovasculaire | D10: Mortalité par maladies cardiovasculaires | E10: oui | F10: Taux standardisé de mortalité par maladies de l'appareil circulatoire (CIM-10 I00-I99), tous âges, France (population standard européenne 2013). | G10: bas | H10: décès pour 100 000 habitants (taux standardisé) | I10: Eurostat (d'après l'INSEE-CépiDc) — hlth_cd_asdr2 (causes de décès, taux standardisés) | J10: hlth_cd_asdr2?freq=A&unit=RT&sex=T&age=TOTAL&icd10=I&geo=FR | K10: 2011-2023 (13 points, annuelle) | L10: resultat | M10: non | N10: non | O10: non | P10: non | Q10: retenir | R10: Deuxième grande cause de décès après les cancers en taux standardisé, série annuelle de 2011 à 2023 (224,76 pour 100 000 en 2011, 163,26 en 2023) sans drapeau. | S10: retenu
A11: causes de décès | B11: mortalite_chutes | C11: mortalite_chutes | D11: Mortalité par chute accidentelle | E11: oui | F11: Taux standardisé de mortalité par chute accidentelle (CIM-10 W00-W19), tous âges, France (population standard européenne 2013). | G11: bas | H11: décès pour 100 000 habitants (taux standardisé) | I11: Eurostat (d'après l'INSEE-CépiDc) — hlth_cd_asdr2 (causes de décès, taux standardisés) | J11: hlth_cd_asdr2?freq=A&unit=RT&sex=T&age=TOTAL&icd10=W00-W19&geo=FR | K11: 2011-2023 (13 points, annuelle) | L11: resultat | M11: non | N11: non | O11: non | P11: non | Q11: retenir | R11: Mesure annuelle des décès par chute de 2011 à 2023, sans drapeau et en hausse de 9,86 à 13,47 pour 100 000, que complète la série de Santé publique France des 65 ans ou plus (2015-2024). | S11: retenu
A12: causes de décès | B12: mortalite_diabete | C12: mortalite_diabete | D12: Mortalité par diabète | E12: oui | F12: Taux standardisé de mortalité par diabète sucré (CIM-10 E10-E14), tous âges, France (population standard européenne 2013). | G12: bas | H12: décès pour 100 000 habitants (taux standardisé) | I12: Eurostat (d'après l'INSEE-CépiDc) — hlth_cd_asdr2 (causes de décès, taux standardisés) | J12: hlth_cd_asdr2?freq=A&unit=RT&sex=T&age=TOTAL&icd10=E10-E14&geo=FR | K12: 2011-2023 (13 points, annuelle) | L12: resultat | M12: non | N12: non | O12: non | P12: non | Q12: retenir | R12: Maladie chronique liée à la nutrition et à la corpulence (A2), série annuelle de 2011 à 2023 sans drapeau (18,26 pour 100 000 en 2011, 15,18 en 2023). | S12: retenu
A13: causes de décès | B13: mortalite_maladies_infectieuses | C13: mortalite_maladies_infectieuses | D13: Mortalité par tuberculose, VIH et hépatites | E13: oui | F13: Taux standardisé de mortalité dû à la tuberculose, au VIH et aux hépatites virales, France (indicateur ODD de l'UE 3.41). | G13: bas | H13: décès pour 100 000 habitants (taux standardisé) | I13: Eurostat (d'après l'INSEE-CépiDc) — sdg_03_41 (mortalité due à la tuberculose, au VIH et à l'hépatite) | J13: sdg_03_41?freq=A&icd10=TOTAL&geo=FR | K13: 2001-2023 (23 points, annuelle) | L13: resultat | M13: non | N13: non | O13: non | P13: non | Q13: retenir | R13: Indicateur de la cible ODD 3.3 (mettre fin aux épidémies), annuel de 2001 à 2023 sans drapeau (5,80 pour 100 000 en 2001, 2,73 en 2011, 1,01 en 2023), seule mesure annuelle des maladies infectieuses au catalogue. | S13: retenu
... A51: santé perçue et limitations | B51: sante_percue | C51: sante_percue_mauvaise | D51: Personnes se déclarant en mauvaise ou très mauvaise santé | E51: non | F51: Part des personnes de 16 ans ou plus vivant en logement ordinaire qui jugent leur état de santé général « mauvais » ou « très mauvais » (enquête SRCV, volet français d'EU-SILC). | G51: bas | H51: % des 16 ans ou plus | I51: Eurostat (d'après l'INSEE, enquête SRCV) — hlth_silc_10 (santé perçue par sexe, âge et quintile de revenu), ensemble des quintiles | J51: hlth_silc_10?freq=A&unit=PC&quant_inc=TOTAL&age=Y_GE16&sex=T&levels=B_VB&geo=FR | K51: 2005-2025 (21 points, annuelle) | L51: resultat | M51: oui | N51: non | O51: non | P51: non | Q51: retenir_variante | R51: Autre lecture de la même question que la part en bonne santé, centrée sur les états de santé dégradés, annuelle de 2005 à 2025 (9,9 % en 2005, 7,7 % en 2015, 10,8 % en 2023, 10,2 % en 2025). | S51: retenu

Sheet Synthèse
A1: Dimension | B1: Santé
A2: Indicateurs candidats (fiches) | B2: =COUNTA(Validation!$C$2:$C$51)
A3: Familles distinctes | B3: =SUMPRODUCT((Validation!$B$2:$B$51<>"")/COUNTIF(Validation!$B$2:$B$51,Validation!$B$2:$B$51&""))
A5: Recommandations de l'agent
A6: retenir | B6: =COUNTIF(Validation!$Q$2:$Q$51,"retenir")
A7: retenir_variante | B7: =COUNTIF(Validation!$Q$2:$Q$51,"retenir_variante")
A8: ecarter | B8: =COUNTIF(Validation!$Q$2:$Q$51,"ecarter")
A10: Socle proposé par l'agent (D41) | B10: =COUNTIF(Validation!$P$2:$P$51,"oui")
A12: Décisions par défaut
A13: retenu_socle | B13: =COUNTIF(Validation!$S$2:$S$51,"retenu_socle")
A14: retenu | B14: =COUNTIF(Validation!$S$2:$S$51,"retenu")
A15: ecarte | B15: =COUNTIF(Validation!$S$2:$S$51,"ecarte")
A16: a_discuter | B16: =COUNTIF(Validation!$S$2:$S$51,"a_discuter")
A18: Vos décisions saisies (exceptions) | B18: =COUNTA(Validation!$T$2:$T$51)
A19: dont retenu_socle | B19: =COUNTIF(Validation!$T$2:$T$51,"retenu_socle")
A20: dont retenu | B20: =COUNTIF(Validation!$T$2:$T$51,"retenu")
A21: dont ecarte | B21: =COUNTIF(Validation!$T$2:$T$51,"ecarte")
A22: dont a_discuter | B22: =COUNTIF(Validation!$T$2:$T$51,"a_discuter")
A24: Socle par sous-thème (D41) | B24: Fiches | C24: retenu_socle par défaut | D24: retenu_socle après vos décisions
A25: accès aux soins | B25: =COUNTIF(Validation!$A$2:$A$51,$A25) | C25: =COUNTIFS(Validation!$A$2:$A$51,$A25,Validation!$S$2:$S$51,"retenu_socle") | D25: =SUMPRODUCT((Validation!$A$2:$A$51=$A25)*(((Validation!$T$2:$T$51="")*(Validation!$S$2:$S$51="retenu_socle"))+(Validation!$T$2:$T$51="retenu_socle")))
A26: causes de décès | B26: =COUNTIF(Validation!$A$2:$A$51,$A26) | C26: =COUNTIFS(Validation!$A$2:$A$51,$A26,Validation!$S$2:$S$51,"retenu_socle") | D26: =SUMPRODUCT((Validation!$A$2:$A$51=$A26)*(((Validation!$T$2:$T$51="")*(Validation!$S$2:$S$51="retenu_socle"))+(Validation!$T$2:$T$51="retenu_socle")))
A27: comportements et prévention | B27: =COUNTIF(Validation!$A$2:$A$51,$A27) | C27: =COUNTIFS(Validation!$A$2:$A$51,$A27,Validation!$S$2:$S$51,"retenu_socle") | D27: =SUMPRODUCT((Validation!$A$2:$A$51=$A27)*(((Validation!$T$2:$T$51="")*(Validation!$S$2:$S$51="retenu_socle"))+(Validation!$T$2:$T$51="retenu_socle")))
A28: espérance de vie | B28: =COUNTIF(Validation!$A$2:$A$51,$A28) | C28: =COUNTIFS(Validation!$A$2:$A$51,$A28,Validation!$S$2:$S$51,"retenu_socle") | D28: =SUMPRODUCT((Validation!$A$2:$A$51=$A28)*(((Validation!$T$2:$T$51="")*(Validation!$S$2:$S$51="retenu_socle"))+(Validation!$T$2:$T$51="retenu_socle")))
A29: maladies infectieuses | B29: =COUNTIF(Validation!$A$2:$A$51,$A29) | C29: =COUNTIFS(Validation!$A$2:$A$51,$A29,Validation!$S$2:$S$51,"retenu_socle") | D29: =SUMPRODUCT((Validation!$A$2:$A$51=$A29)*(((Validation!$T$2:$T$51="")*(Validation!$S$2:$S$51="retenu_socle"))+(Validation!$T$2:$T$51="retenu_socle")))
A30: mortalité | B30: =COUNTIF(Validation!$A$2:$A$51,$A30) | C30: =COUNTIFS(Validation!$A$2:$A$51,$A30,Validation!$S$2:$S$51,"retenu_socle") | D30: =SUMPRODUCT((Validation!$A$2:$A$51=$A30)*(((Validation!$T$2:$T$51="")*(Validation!$S$2:$S$51="retenu_socle"))+(Validation!$T$2:$T$51="retenu_socle")))
A31: perceptions | B31: =COUNTIF(Validation!$A$2:$A$51,$A31) | C31: =COUNTIFS(Validation!$A$2:$A$51,$A31,Validation!$S$2:$S$51,"retenu_socle") | D31: =SUMPRODUCT((Validation!$A$2:$A$51=$A31)*(((Validation!$T$2:$T$51="")*(Validation!$S$2:$S$51="retenu_socle"))+(Validation!$T$2:$T$51="retenu_socle")))
A32: périnatalité | B32: =COUNTIF(Validation!$A$2:$A$51,$A32) | C32: =COUNTIFS(Validation!$A$2:$A$51,$A32,Validation!$S$2:$S$51,"retenu_socle") | D32: =SUMPRODUCT((Validation!$A$2:$A$51=$A32)*(((Validation!$T$2:$T$51="")*(Validation!$S$2:$S$51="retenu_socle"))+(Validation!$T$2:$T$51="retenu_socle")))
A33: santé mentale | B33: =COUNTIF(Validation!$A$2:$A$51,$A33) | C33: =COUNTIFS(Validation!$A$2:$A$51,$A33,Validation!$S$2:$S$51,"retenu_socle") | D33: =SUMPRODUCT((Validation!$A$2:$A$51=$A33)*(((Validation!$T$2:$T$51="")*(Validation!$S$2:$S$51="retenu_socle"))+(Validation!$T$2:$T$51="retenu_socle")))
A34: santé perçue et limitations | B34: =COUNTIF(Validation!$A$2:$A$51,$A34) | C34: =COUNTIFS(Validation!$A$2:$A$51,$A34,Validation!$S$2:$S$51,"retenu_socle") | D34: =SUMPRODUCT((Validation!$A$2:$A$51=$A34)*(((Validation!$T$2:$T$51="")*(Validation!$S$2:$S$51="retenu_socle"))+(Validation!$T$2:$T$51="retenu_socle")))
A35: Total | B35: =SUM(B25:B34) | C35: =SUM(C25:C34) | D35: =SUM(D25:D34)
A37: Les comptes se recalculent à l'ouverture dans Excel.
